{"errors":[],"warnings":[],"namedChunkGroups":{"app":{"chunks":[9,0,2],"assets":["webpack-runtime-8e6f6441a4ef743bfdea.js","webpack-runtime-8e6f6441a4ef743bfdea.js.map","commons-67bf7de4a383a7f492f3.js","commons-67bf7de4a383a7f492f3.js.map","app-988b02e9258cfd3d62b5.js","app-988b02e9258cfd3d62b5.js.map"],"children":{},"childAssets":{}},"component---src-templates-blog-js":{"chunks":[1,0,8],"assets":["styles.cf8f5988271057e9770e.css","styles-157858261724a35c149b.js","styles-157858261724a35c149b.js.map","commons-67bf7de4a383a7f492f3.js","commons-67bf7de4a383a7f492f3.js.map","component---src-templates-blog-js-35b5a73ed9946167080a.js","component---src-templates-blog-js-35b5a73ed9946167080a.js.map"],"children":{},"childAssets":{}},"component---src-pages-404-js":{"chunks":[1,0,3],"assets":["styles.cf8f5988271057e9770e.css","styles-157858261724a35c149b.js","styles-157858261724a35c149b.js.map","commons-67bf7de4a383a7f492f3.js","commons-67bf7de4a383a7f492f3.js.map","component---src-pages-404-js-ad0efa134b2b37792516.js","component---src-pages-404-js-ad0efa134b2b37792516.js.map"],"children":{},"childAssets":{}},"component---src-pages-about-js":{"chunks":[1,0,4],"assets":["styles.cf8f5988271057e9770e.css","styles-157858261724a35c149b.js","styles-157858261724a35c149b.js.map","commons-67bf7de4a383a7f492f3.js","commons-67bf7de4a383a7f492f3.js.map","component---src-pages-about-js-bcab3f7cc6e348e6c11f.js","component---src-pages-about-js-bcab3f7cc6e348e6c11f.js.map"],"children":{},"childAssets":{}},"component---src-pages-blog-js":{"chunks":[1,0,5],"assets":["styles.cf8f5988271057e9770e.css","styles-157858261724a35c149b.js","styles-157858261724a35c149b.js.map","commons-67bf7de4a383a7f492f3.js","commons-67bf7de4a383a7f492f3.js.map","component---src-pages-blog-js-cb9987eedfcc5249bd3e.js","component---src-pages-blog-js-cb9987eedfcc5249bd3e.js.map"],"children":{},"childAssets":{}},"component---src-pages-contact-js":{"chunks":[1,0,6],"assets":["styles.cf8f5988271057e9770e.css","styles-157858261724a35c149b.js","styles-157858261724a35c149b.js.map","commons-67bf7de4a383a7f492f3.js","commons-67bf7de4a383a7f492f3.js.map","component---src-pages-contact-js-0cea368dc3be78a6ead8.js","component---src-pages-contact-js-0cea368dc3be78a6ead8.js.map"],"children":{},"childAssets":{}},"component---src-pages-index-js":{"chunks":[1,0,7],"assets":["styles.cf8f5988271057e9770e.css","styles-157858261724a35c149b.js","styles-157858261724a35c149b.js.map","commons-67bf7de4a383a7f492f3.js","commons-67bf7de4a383a7f492f3.js.map","component---src-pages-index-js-146f1e3a862a82c3e743.js","component---src-pages-index-js-146f1e3a862a82c3e743.js.map"],"children":{},"childAssets":{}}},"assetsByChunkName":{"app":["webpack-runtime-8e6f6441a4ef743bfdea.js","commons-67bf7de4a383a7f492f3.js","app-988b02e9258cfd3d62b5.js"],"component---src-templates-blog-js":["styles.cf8f5988271057e9770e.css","styles-157858261724a35c149b.js","commons-67bf7de4a383a7f492f3.js","component---src-templates-blog-js-35b5a73ed9946167080a.js"],"component---src-pages-404-js":["styles.cf8f5988271057e9770e.css","styles-157858261724a35c149b.js","commons-67bf7de4a383a7f492f3.js","component---src-pages-404-js-ad0efa134b2b37792516.js"],"component---src-pages-about-js":["styles.cf8f5988271057e9770e.css","styles-157858261724a35c149b.js","commons-67bf7de4a383a7f492f3.js","component---src-pages-about-js-bcab3f7cc6e348e6c11f.js"],"component---src-pages-blog-js":["styles.cf8f5988271057e9770e.css","styles-157858261724a35c149b.js","commons-67bf7de4a383a7f492f3.js","component---src-pages-blog-js-cb9987eedfcc5249bd3e.js"],"component---src-pages-contact-js":["styles.cf8f5988271057e9770e.css","styles-157858261724a35c149b.js","commons-67bf7de4a383a7f492f3.js","component---src-pages-contact-js-0cea368dc3be78a6ead8.js"],"component---src-pages-index-js":["styles.cf8f5988271057e9770e.css","styles-157858261724a35c149b.js","commons-67bf7de4a383a7f492f3.js","component---src-pages-index-js-146f1e3a862a82c3e743.js"]}}